README.rst
setup.cfg
setup.py
stubserver/__init__.py
stubserver/ftpserver.py
stubserver/webserver.py
stubserver.egg-info/PKG-INFO
stubserver.egg-info/SOURCES.txt
stubserver.egg-info/dependency_links.txt
stubserver.egg-info/top_level.txt