Metadata-Version: 1.1
Name: stubserver
Version: 1.1
Summary: A stub webserver used to enable blackbox testing of applications that call external web urls. For example, an application that consumes data from an external REST api. The usage pattern is intended to be very much like using a mock framework.
Home-page: http://www.pyruby.com/pythonstubserver
Author: Chris Tarttelin and Point 2 inc
Author-email: chris@pyruby.co.uk
License: FreeBSD
Keywords: test,unittest,mock,http,ftp
Platform: UNKNOWN
Classifier: Intended Audience :: Developers
Classifier: License :: OSI Approved :: BSD License
Classifier: Operating System :: OS Independent
Classifier: Programming Language :: Python
Classifier: Programming Language :: Python :: 2.7
